MANIFEST.in
README
README.md
daff.py
package.json
setup.py
daff/__init__.py
daff.egg-info/PKG-INFO
daff.egg-info/SOURCES.txt
daff.egg-info/dependency_links.txt
daff.egg-info/entry_points.txt
daff.egg-info/top_level.txt
test/test_example.py
test/test_sqlite.py