Metadata-Version: 1.1
Name: daff
Version: 1.3.39
Summary: Diff and patch tables
Home-page: https://github.com/paulfitz/daff
Author: Paul Fitzpatrick
Author-email: paul@robotrebuilt.com
License: MIT
Keywords: data diff patch
Platform: UNKNOWN
Classifier: Development Status :: 3 - Alpha
Classifier: Topic :: Utilities
Classifier: License :: OSI Approved :: MIT License
